{"nodes": [{"id": "assets_lumen_logo", "label": "Lumen App Logo", "file_type": "image", "source_file": "assets/lumen.png", "source_location": null, "source_url": null, "captured_at": null, "author": null, "contributor": null}, {"id": "assets_lumen_amber_light_point", "label": "Central Glowing Amber Light Point", "file_type": "concept", "source_file": "assets/lumen.png", "source_location": null, "source_url": null, "captured_at": null, "author": null, "contributor": null}, {"id": "assets_lumen_concentric_rings", "label": "Embossed Concentric Rings Motif", "file_type": "concept", "source_file": "assets/lumen.png", "source_location": null, "source_url": null, "captured_at": null, "author": null, "contributor": null}, {"id": "assets_lumen_dark_squircle", "label": "Dark Charcoal Rounded-Square Icon Shape", "file_type": "concept", "source_file": "assets/lumen.png", "source_location": null, "source_url": null, "captured_at": null, "author": null, "contributor": null}, {"id": "assets_lumen_light_metaphor", "label": "Lumen Name as Light Metaphor", "file_type": "rationale", "source_file": "assets/lumen.png", "source_location": null, "source_url": null, "captured_at": null, "author": null, "contributor": null}, {"id": "assets_lumen_refined_dark_amber_aesthetic", "label": "Refined-Dark Aesthetic with Amber Accent", "file_type": "concept", "source_file": "assets/lumen.png", "source_location": null, "source_url": null, "captured_at": null, "author": null, "contributor": null}, {"id": "assets_lumen_resolution_variants", "label": "Logo 1x/2x/3x Resolution Variants", "file_type": "concept", "source_file": "assets/lumen.png", "source_location": null, "source_url": null, "captured_at": null, "author": null, "contributor": null}], "edges": [{"source": "assets_lumen_logo", "target": "assets_lumen_amber_light_point", "relation": "references", "confidence": "EXTRACTED", "confidence_score": 1.0, "source_file": "assets/lumen.png", "source_location": null, "weight": 1.0}, {"source": "assets_lumen_logo", "target": "assets_lumen_concentric_rings", "relation": "references", "confidence": "EXTRACTED", "confidence_score": 1.0, "source_file": "assets/lumen.png", "source_location": null, "weight": 1.0}, {"source": "assets_lumen_logo", "target": "assets_lumen_dark_squircle", "relation": "references", "confidence": "EXTRACTED", "confidence_score": 1.0, "source_file": "assets/lumen.png", "source_location": null, "weight": 1.0}, {"source": "assets_lumen_light_metaphor", "target": "assets_lumen_logo", "relation": "rationale_for", "confidence": "INFERRED", "confidence_score": 0.85, "source_file": "assets/lumen.png", "source_location": null, "weight": 1.0}, {"source": "assets_lumen_amber_light_point", "target": "assets_lumen_light_metaphor", "relation": "conceptually_related_to", "confidence": "INFERRED", "confidence_score": 0.85, "source_file": "assets/lumen.png", "source_location": null, "weight": 1.0}, {"source": "assets_lumen_concentric_rings", "target": "assets_lumen_light_metaphor", "relation": "conceptually_related_to", "confidence": "INFERRED", "confidence_score": 0.75, "source_file": "assets/lumen.png", "source_location": null, "weight": 1.0}, {"source": "assets_lumen_logo", "target": "assets_lumen_refined_dark_amber_aesthetic", "relation": "implements", "confidence": "INFERRED", "confidence_score": 0.85, "source_file": "assets/lumen.png", "source_location": null, "weight": 1.0}, {"source": "assets_lumen_amber_light_point", "target": "assets_lumen_refined_dark_amber_aesthetic", "relation": "conceptually_related_to", "confidence": "INFERRED", "confidence_score": 0.85, "source_file": "assets/lumen.png", "source_location": null, "weight": 1.0}, {"source": "assets_lumen_dark_squircle", "target": "assets_lumen_refined_dark_amber_aesthetic", "relation": "conceptually_related_to", "confidence": "INFERRED", "confidence_score": 0.75, "source_file": "assets/lumen.png", "source_location": null, "weight": 1.0}, {"source": "assets_lumen_logo", "target": "assets_lumen_resolution_variants", "relation": "references", "confidence": "EXTRACTED", "confidence_score": 1.0, "source_file": "assets/lumen.png", "source_location": null, "weight": 1.0}], "hyperedges": []}